jabs/vision/__init__.py
jabs_vision-0.1.0.dist-info/WHEEL
jabs_vision-0.1.0.dist-info/METADATA
jabs_vision-0.1.0.dist-info/RECORD
