Metadata-Version: 2.3
Name: jabs-vision
Version: 0.1.0
Summary: 
Author: Glen Beane, Alexander Berger-Liedtka, Keith Sheppard
License: Proprietary
Requires-Dist: jabs-io
Requires-Dist: jabs-core
Requires-Dist: hydra-core>=1.3.2
Requires-Dist: torch>=2.9.1
Requires-Dist: torchvision>=0.24.1
Requires-Dist: mlflow>=3.8.1 ; extra == 'mlflow'
Requires-Dist: matplotlib>=3.10.8 ; extra == 'plot'
Requires-Dist: submitit>=1.5.4 ; extra == 'submitit'
Requires-Dist: timm>=1.0.0 ; extra == 'timm'
Requires-Dist: wandb>=0.24.0 ; extra == 'wandb'
Requires-Python: >=3.10, <3.15
Project-URL: Repository, https://github.com/KumarLabJax/JABS-behavior-classifier
Project-URL: Issues, https://github.com/KumarLabJax/JABS-behavior-classifier/issues
Provides-Extra: mlflow
Provides-Extra: plot
Provides-Extra: submitit
Provides-Extra: timm
Provides-Extra: wandb
